atooms/__init__.py
atooms/active/__init__.py
atooms/active/api.py
atooms/active/neighbor_list.f90
atooms/active/neighbor_list_newton.f90
atooms/active/neighbor_list_newton_inline.f90
atooms/active/neighbors.py
atooms/active/vicsek.py
atooms.active-1.0.5.dist-info/LICENSE
atooms.active-1.0.5.dist-info/METADATA
atooms.active-1.0.5.dist-info/WHEEL
atooms.active-1.0.5.dist-info/entry_points.txt
atooms.active-1.0.5.dist-info/top_level.txt
atooms.active-1.0.5.dist-info/RECORD
