Metadata-Version: 2.1
Name: atooms.active
Version: 1.0.5
Summary: An atooms backend for simulating active matter
Author: Iacopo Ricci
License: GPLv3
Project-URL: repository, https://framagit.org/atooms/active
Project-URL: changelog, https://framagit.org/atooms/active/-/blob/master/CHANGELOG.md
Classifier: License :: OSI Approved :: GNU General Public License v3 (GPLv3)
Classifier: Programming Language :: Python :: 3.10
Classifier: Development Status :: 5 - Production/Stable
Classifier: Intended Audience :: Science/Research
Classifier: Topic :: Scientific/Engineering :: Physics
Requires-Python: >=3.10
License-File: LICENSE
Requires-Dist: argh >=0.28.1
Requires-Dist: atooms >=3.15.0
Requires-Dist: f2py-jit >=0.9.1
Requires-Dist: numpy
Provides-Extra: full
Requires-Dist: scipy ; extra == 'full'
